sabyenc3.cpython-310-i386-linux-gnu.so
sabyenc3-5.4.4.dist-info/top_level.txt
sabyenc3-5.4.4.dist-info/WHEEL
sabyenc3-5.4.4.dist-info/METADATA
sabyenc3-5.4.4.dist-info/LICENSE.md
sabyenc3-5.4.4.dist-info/RECORD
