Metadata-Version: 2.1
Name: sabyenc3
Version: 5.4.4
Summary: yEnc decoding of usenet data using SIMD routines
Home-page: https://github.com/sabnzbd/sabyenc/
Author: Safihre
Author-email: safihre@sabnzbd.org
License: LGPLv3
Classifier: Programming Language :: Python
Classifier: Programming Language :: Python :: 3 :: Only
Classifier: Programming Language :: C
Classifier: License :: OSI Approved :: GNU Lesser General Public License v3 (LGPLv3)
Classifier: Operating System :: Unix
Classifier: Development Status :: 5 - Production/Stable
Classifier: Environment :: Plugins
Classifier: Topic :: Software Development :: Libraries :: Python Modules
Classifier: Topic :: Communications :: Usenet News
License-File: LICENSE.md
